{
    "cliVersion": "5.6.1",
    "generatorName": "fernapi/fern-typescript-sdk",
    "generatorVersion": "3.66.1",
    "generatorConfig": {
        "namespaceExport": "Junction",
        "noSerdeLayer": false,
        "omitUndefined": false,
        "skipResponseValidation": false,
        "fileResponseType": "binary-response",
        "formDataSupport": "Node18",
        "fetchSupport": "native",
        "packageManager": "pnpm",
        "testFramework": "vitest"
    },
    "originGitCommit": "e1c3ceef9f4e6957d1a38d66920fdb58ec00c6d5",
    "originGitCommitIsDirty": true,
    "invokedBy": "ci",
    "requestedVersion": "AUTO",
    "ciProvider": "unknown",
    "sdkVersion": "1.0.0"
}
